Epytoml/EpyBake.py
Epytoml/Meaningless.py
Epytoml/Notaker.py
Epytoml/ShortcutMiner.py
Epytoml/__init__.py
Epytoml-1.2.1.1.dist-info/LICENSE.md
Epytoml-1.2.1.1.dist-info/METADATA
Epytoml-1.2.1.1.dist-info/WHEEL
Epytoml-1.2.1.1.dist-info/top_level.txt
Epytoml-1.2.1.1.dist-info/RECORD
