Metadata-Version: 2.1
Name: Epytoml
Version: 1.2.1.1
Summary: A python library that converts plain text into a specified markup language using python.
Home-page: https://github.com/Z1aaan/Epytoml
Author: Zhean Robby Ganituen
Author-email: zheanrobbyganituen@gmail.com
License: MIT License
Platform: UNKNOWN
License-File: LICENSE.md
Requires-Dist: pdfkit
Requires-Dist: tkDocViewer
Requires-Dist: tkPDFViewer
Requires-Dist: PyPDF2
Requires-Dist: lorem
